{
    "balance": 91928.20010000012,
    "name": "Python",
    "cryptowallet": [
        {
            "amount": 12,
            "price": 50765.85267345925,
            "cryptoName": "Bitcoin",
            "cryptoCode": "BTC"
        },
        {
            "amount": 105,
            "price": 3159.617358611414,
            "cryptoName": "Ethereum",
            "cryptoCode": "ETH"
        },
        {
            "amount": 10000,
            "price": 1.4479469790522919,
            "cryptoName": "Cardano",
            "cryptoCode": "ADA"
        },
        {
            "amount": 20,
            "price": 0.9708642562500002,
            "cryptoName": "Ripple",
            "cryptoCode": "XRP"
        }
    ]
}